{
  "parent": "minecraft:recipes/root",
  "criteria": {
    "has_blank_snow_block_carving": {
      "conditions": {
        "items": [
          {
            "items": [
              "chipped:blank_snow_block_carving"
            ]
          }
        ]
      },
      "trigger": "minecraft:inventory_changed"
    },
    "has_the_recipe": {
      "conditions": {
        "recipe": "minecraft:blank_snow_block_carving_layer_from_blank_snow_block_carving_layer_vertical_stonecutting"
      },
      "trigger": "minecraft:recipe_unlocked"
    }
  },
  "requirements": [
    [
      "has_blank_snow_block_carving",
      "has_the_recipe"
    ]
  ],
  "rewards": {
    "recipes": [
      "minecraft:blank_snow_block_carving_layer_from_blank_snow_block_carving_layer_vertical_stonecutting"
    ]
  },
  "sends_telemetry_event": false
}