{
  "parent": "minecraft:recipes/root",
  "criteria": {
    "has_etched_dark_prismarine_bricks": {
      "conditions": {
        "items": [
          {
            "items": [
              "chipped:etched_dark_prismarine_bricks"
            ]
          }
        ]
      },
      "trigger": "minecraft:inventory_changed"
    },
    "has_the_recipe": {
      "conditions": {
        "recipe": "minecraft:etched_dark_prismarine_brick_arrowslit_from_etched_dark_prismarine_bricks_stonecutting"
      },
      "trigger": "minecraft:recipe_unlocked"
    }
  },
  "requirements": [
    [
      "has_etched_dark_prismarine_bricks",
      "has_the_recipe"
    ]
  ],
  "rewards": {
    "recipes": [
      "minecraft:etched_dark_prismarine_brick_arrowslit_from_etched_dark_prismarine_bricks_stonecutting"
    ]
  },
  "sends_telemetry_event": false
}