{
  "parent": "minecraft:recipes/root",
  "criteria": {
    "has_the_recipe": {
      "conditions": {
        "recipe": "minecraft:tiled_andesite_arch_half_from_tiled_andesite_stonecutting"
      },
      "trigger": "minecraft:recipe_unlocked"
    },
    "has_tiled_andesite": {
      "conditions": {
        "items": [
          {
            "items": [
              "chipped:tiled_andesite"
            ]
          }
        ]
      },
      "trigger": "minecraft:inventory_changed"
    }
  },
  "requirements": [
    [
      "has_tiled_andesite",
      "has_the_recipe"
    ]
  ],
  "rewards": {
    "recipes": [
      "minecraft:tiled_andesite_arch_half_from_tiled_andesite_stonecutting"
    ]
  },
  "sends_telemetry_event": false
}