{
  "parent": "minecraft:recipes/root",
  "rewards": {
    "recipes": [
      "minecraft:acacia_board_slab_from_acacia_boards_shaped"
    ]
  },
  "criteria": {
    "has_acacia_boards": {
      "trigger": "minecraft:inventory_changed",
      "conditions": {
        "items": [
          {
            "items": [
              "caliber:acacia_boards"
            ]
          }
        ]
      }
    },
    "has_the_recipe": {
      "trigger": "minecraft:recipe_unlocked",
      "conditions": {
        "recipe": "minecraft:acacia_board_slab_from_acacia_boards_shaped"
      }
    }
  },
  "requirements": [
    [
      "has_acacia_boards",
      "has_the_recipe"
    ]
  ]
}