{
  "parent": "minecraft:recipes/root",
  "rewards": {
    "recipes": [
      "minecraft:jungle_boards_stairs_from_shaped_acacia_boards_"
    ]
  },
  "criteria": {
    "has_jungle_boards_": {
      "trigger": "minecraft:inventory_changed",
      "conditions": {
        "items": [
          {
            "items": [
              "caliber:jungle_boards"
            ]
          }
        ]
      }
    },
    "has_the_recipe": {
      "trigger": "minecraft:recipe_unlocked",
      "conditions": {
        "recipe": "minecraft:jungle_boards_stairs_from_shaped_acacia_boards_"
      }
    }
  },
  "requirements": [
    [
      "has_jungle_boards_",
      "has_the_recipe"
    ]
  ]
}