{
  "parent": "minecraft:recipes/root",
  "rewards": {
    "recipes": [
      "minecraft:tudor_jungle_white_plaster_down_from_jungle_planks_white_plaster"
    ]
  },
  "criteria": {
    "has_white_plaster": {
      "trigger": "minecraft:inventory_changed",
      "conditions": {
        "items": [
          {
            "items": [
              "caliber:white_plaster"
            ]
          }
        ]
      }
    },
    "has_the_recipe": {
      "trigger": "minecraft:recipe_unlocked",
      "conditions": {
        "recipe": "minecraft:tudor_jungle_white_plaster_down_from_jungle_planks_white_plaster"
      }
    }
  },
  "requirements": [
    [
      "has_white_plaster",
      "has_the_recipe"
    ]
  ]
}